fifo/rtl/fifo.v
module fifo (
    input clk,
    input rst_n,

    input write_en,
    input read_en,

    input [7:0] data_in,
    output reg [7:0] data_out,

    output full,
    output empty

);

reg [3:0] wptr;                               // 4 bit write pointer 
reg [3:0] rdptr;                              // 4 bit read pointer

reg [7:0] mem [7:0];                          // 8 bit memory array with depth of 8

always @ (posedge clk or negedge rst_n) begin
    if (!rst_n) begin
        wptr <= 4'b0;
        rdptr <= 4'b0;      
    end

    else begin
        if (write_en && !full) begin 
            mem[wptr[2:0]] <= data_in;
            wptr <= wptr + 1'b1;
        end
        if (read_en && !empty) begin
            data_out <= mem[rdptr[2:0]];
            rdptr <= rdptr + 1'b1;
        end
    
    end
end
assign empty = wptr == rdptr;
assign full = ((wptr[3] != rdptr[3]) && (wptr[2:0] == rdptr[2:0])) ;

endmodule

fifo/rtl/tb_fifo.v

`timescale 1ns/1ns
module tb;
reg clk,rst_n,w_en,r_en;
reg [7:0] data_in; 

wire [7:0] data_out;
wire full,empty;

fifo dut (
    .clk(clk),
    .rst_n(rst_n),
    .write_en(w_en),
    .read_en(r_en),
    .data_in(data_in),
    .data_out(data_out),
    .full(full),
    .empty(empty)
);

always #5 clk = ~clk;

initial begin
    clk = 0;
    rst_n = 0;
    #10 rst_n = 1;
end


initial begin 
    $monitor("rst_n = %0d || w_en = %0d || r_en = %0d || data_in = %0h || data_out =%0h || full = %0b || empty = %0b", 
    rst_n, w_en, r_en, data_in , data_out, full, empty);

    
    // write(8);
    @ (negedge clk);
    @ (negedge clk);
    repeat (8) begin
        @ (negedge clk);
        w_en = 1'b1;
        data_in = $random; 
    end
    @(negedge clk);
    w_en = 1'b0;
    if (full) $display("TEST 1: fifo write test passed");
    else $display("TEST 1: fifo write test failed");

    @(negedge clk);

    r_en = 1'b1;
    repeat (8) @(negedge clk);
    r_en = 1'b0;
    if (empty) $display("TEST 2: fifo read test passed");
    else $display("TEST 2: fifo read test failed");

    @(negedge clk);

    @ (negedge clk);
    repeat (8) begin
        @ (negedge clk);
        data_in = $random; 
        w_en = 1'b1;
    end
    @(negedge clk);
    w_en = 1'b0;
    @(negedge clk);
    r_en = 1'b1;
    repeat (8) @(negedge clk);
    r_en = 1'b0;
    if (empty) $display("TEST 3: fifo read after write test passed");
    else $display("TEST 3: fifo read after write test failed");

    @(negedge clk);

    fork
        begin
            repeat (16) begin
                @ (negedge clk);
                data_in = $random; 
                w_en = 1'b1;
            end
            @(negedge clk);
            w_en = 1'b0;
        end
        begin            
            @(negedge clk);
            r_en = 1'b1;
            repeat (9) @(negedge clk);
            r_en = 1'b0;
        end
    join
    if (full) $display("TEST 4: fifo 2 write and 1 read test passed");
    else $display("TEST 4: fifo 2 write and 1 read test failed");


    #10 $finish;

end

initial begin
    $dumpfile ("tb_fifo.vcd");
    $dumpvars(0,tb);
end

endmodule

fifo/rtl/tb_fifo.vcd
$date
	Thu Aug 20 02:04:46 2026
$end
$version
	Icarus Verilog
$end
$timescale
	1ns
$end
$scope module tb $end
$var wire 1 ! full $end
$var wire 1 " empty $end
$var wire 8 # data_out [7:0] $end
$var reg 1 $ clk $end
$var reg 8 % data_in [7:0] $end
$var reg 1 & r_en $end
$var reg 1 ' rst_n $end
$var reg 1 ( w_en $end
$scope module dut $end
$var wire 1 $ clk $end
$var wire 8 ) data_in [7:0] $end
$var wire 1 ! full $end
$var wire 1 & read_en $end
$var wire 1 ' rst_n $end
$var wire 1 ( write_en $end
$var wire 1 " empty $end
$var reg 8 * data_out [7:0] $end
$var reg 4 + rdptr [3:0] $end
$var reg 4 , wptr [3:0] $end
$upscope $end
$upscope $end
$enddefinitions $end
#0
$dumpvars
b0 ,
b0 +
bx *
bx )
x(
0'
x&
bx %
0$
bx #
1"
0!
$end
#5
1$
#10
0$
1'
#15
1$
#20
0$
#25
1$
#30
b100100 %
b100100 )
1(
0$
#35
0"
b1 ,
1$
#40
b10000001 %
b10000001 )
0$
#45
b10 ,
1$
#50
b1001 %
b1001 )
0$
#55
b11 ,
1$
#60
b1100011 %
b1100011 )
0$
#65
b100 ,
1$
#70
b1101 %
b1101 )
0$
#75
b101 ,
1$
#80
b10001101 %
b10001101 )
0$
#85
b110 ,
1$
#90
b1100101 %
b1100101 )
0$
#95
b111 ,
1$
#100
b10010 %
b10010 )
0$
#105
1!
b1000 ,
1$
#110
0(
0$
#115
1$
#120
1&
0$
#125
0!
b1 +
b100100 #
b100100 *
1$
#130
0$
#135
b10 +
b10000001 #
b10000001 *
1$
#140
0$
#145
b11 +
b1001 #
b1001 *
1$
#150
0$
#155
b100 +
b1100011 #
b1100011 *
1$
#160
0$
#165
b101 +
b1101 #
b1101 *
1$
#170
0$
#175
b110 +
b10001101 #
b10001101 *
1$
#180
0$
#185
b111 +
b1100101 #
b1100101 *
1$
#190
0$
#195
0!
1"
b1000 +
b10010 #
b10010 *
1$
#200
0&
0$
#205
1$
#210
0$
#215
1$
#220
0$
#225
1$
#230
1(
b1 %
b1 )
0$
#235
0"
b1001 ,
1$
#240
b1101 %
b1101 )
0$
#245
b1010 ,
1$
#250
b1110110 %
b1110110 )
0$
#255
b1011 ,
1$
#260
b111101 %
b111101 )
0$
#265
b1100 ,
1$
#270
b11101101 %
b11101101 )
0$
#275
b1101 ,
1$
#280
b10001100 %
b10001100 )
0$
#285
b1110 ,
1$
#290
b11111001 %
b11111001 )
0$
#295
b1111 ,
1$
#300
b11000110 %
b11000110 )
0$
#305
1!
b0 ,
1$
#310
0(
0$
#315
1$
#320
1&
0$
#325
0!
b1001 +
b1 #
b1 *
1$
#330
0$
#335
b1010 +
b1101 #
b1101 *
1$
#340
0$
#345
b1011 +
b1110110 #
b1110110 *
1$
#350
0$
#355
b1100 +
b111101 #
b111101 *
1$
#360
0$
#365
b1101 +
b11101101 #
b11101101 *
1$
#370
0$
#375
b1110 +
b10001100 #
b10001100 *
1$
#380
0$
#385
b1111 +
b11111001 #
b11111001 *
1$
#390
0$
#395
0!
1"
b0 +
b11000110 #
b11000110 *
1$
#400
0&
0$
#405
1$
#410
0$
#415
1$
#420
1&
1(
b11000101 %
b11000101 )
0$
#425
0"
b1 ,
1$
#430
b10101010 %
b10101010 )
0$
#435
b1 +
b11000101 #
b11000101 *
b10 ,
1$
#440
b11100101 %
b11100101 )
0$
#445
b10 +
b10101010 #
b10101010 *
b11 ,
1$
#450
b1110111 %
b1110111 )
0$
#455
b11 +
b11100101 #
b11100101 *
b100 ,
1$
#460
b10010 %
b10010 )
0$
#465
b100 +
b1110111 #
b1110111 *
b101 ,
1$
#470
b10001111 %
b10001111 )
0$
#475
b101 +
b10010 #
b10010 *
b110 ,
1$
#480
b11110010 %
b11110010 )
0$
#485
b110 +
b10001111 #
b10001111 *
b111 ,
1$
#490
b11001110 %
b11001110 )
0$
#495
b111 +
b11110010 #
b11110010 *
b1000 ,
1$
#500
b11101000 %
b11101000 )
0$
#505
b1000 +
b11001110 #
b11001110 *
b1001 ,
1$
#510
b11000101 %
b11000101 )
0&
0$
#515
b1010 ,
1$
#520
b1011100 %
b1011100 )
0$
#525
b1011 ,
1$
#530
b10111101 %
b10111101 )
0$
#535
b1100 ,
1$
#540
b101101 %
b101101 )
0$
#545
b1101 ,
1$
#550
b1100101 %
b1100101 )
0$
#555
b1110 ,
1$
#560
b1100011 %
b1100011 )
0$
#565
b1111 ,
1$
#570
b1010 %
b1010 )
0$
#575
1!
b0 ,
1$
#580
0(
0$
